graphflex/__init__.py
graphflex/connectors/__init__.py
graphflex/connectors/base.py
graphflex/connectors/cypher.py
graphflex/connectors/dgl.py
graphflex/connectors/hdt.py
graphflex/connectors/local.py
graphflex/connectors/sparql.py
graphflex/functions/__init__.py
graphflex/functions/edgenode.py
graphflex/functions/feature.py
graphflex/functions/postprocessing/__init__.py
graphflex/functions/postprocessing/base.py
graphflex/functions/postprocessing/filter.py
graphflex/graphflex.py
graphflex/neighbourhood/__init__.py
graphflex/neighbourhood/base.py
graphflex/neighbourhood/extractor.py
graphflex-0.1.0.dist-info/LICENSE
graphflex-0.1.0.dist-info/METADATA
graphflex-0.1.0.dist-info/WHEEL
graphflex-0.1.0.dist-info/RECORD
