Metadata-Version: 2.3
Name: graphflex
Version: 0.1.0
Summary: Flexible Framework for Graph Feature Engineering
License: MIT
Keywords: graph,feafture-engineering
Author: Bram Steenwinckel
Author-email: bram.steenwinckel@ugent.be
Requires-Python: >=3.10
Classifier: License :: OSI Approved :: MIT License
Classifier: Programming Language :: Python :: 3
Classifier: Programming Language :: Python :: 3.10
Classifier: Programming Language :: Python :: 3.11
Classifier: Programming Language :: Python :: 3.12
Classifier: Programming Language :: Python :: 3.13
Provides-Extra: dgl
Provides-Extra: full
Provides-Extra: neo4j
Provides-Extra: rdflib
Requires-Dist: PyYAML (>=6.0.2) ; extra == "dgl" or extra == "full"
Requires-Dist: dgl (==2.1.0) ; extra == "dgl" or extra == "full"
Requires-Dist: neo4j (>=5.28.1) ; extra == "neo4j" or extra == "full"
Requires-Dist: numpy (>=1.26,<2.0)
Requires-Dist: pandas (>=2.2.3,<3.0.0)
Requires-Dist: pydantic (>=2.10.6) ; extra == "dgl" or extra == "full"
Requires-Dist: rdflib-hdt (>=3.1) ; extra == "rdflib"
Requires-Dist: scikit-learn (>=1.6.1,<2.0.0)
Requires-Dist: torch (==2.0.1) ; extra == "dgl" or extra == "full"
Requires-Dist: torchdata (==0.6.1) ; extra == "dgl" or extra == "full"
Requires-Dist: tqdm (>=4.67,<5.0)
Project-URL: Documentation, https://github.com/predict-idlab/graphflex
Project-URL: Homepage, https://github.com/predict-idlab/graphflex
Project-URL: Repository, https://github.com/predict-idlab/graphflex
